{
  "schemaVersion": 1,
  "id": "ultraopt",
  "version": "${version}",
  "name": "UltraOpt",
  "description": "Extreme performance optimization mod for Minecraft",
  "authors": ["Jakub"],
  "contact": {
    "sources": "https://github.com/Jakub668/UltraOpt"
  },
  "license": "MIT",
  "environment": "*",
  "entrypoints": {
    "main": [
      "pl.jakub.ultraopt.UltraOpt"
    ]
  },
  "mixins": [
    "ultraopt.mixins.json"
  ],
  "depends": {
    "fabricloader": ">=0.15.7",
    "minecraft": "1.21.4"
  }
}
